{"bmitickets": 88.79, "bmitickets_30": 37, "bmitickets_365": 105, "bmitickets_7": 0, "changed": 216, "changed_30": 6, "changed_365": 129, "changed_7": 0, "changers": 126, "changers_30": 6, "changers_365": 79, "changers_7": 0, "closed": 206, "closed_30": 3, "closed_365": 119, "closed_7": 0, "closers": 49, "closers_30": 3, "closers_365": 33, "closers_7": 0, "diff_netbmitickets_30": 4, "diff_netbmitickets_365": 10, "diff_netbmitickets_7": 0, "diff_netchanged_30": 3, "diff_netchanged_365": 43, "diff_netchanged_7": -2, "diff_netchangers_30": 4, "diff_netchangers_365": 45, "diff_netchangers_7": -2, "diff_netclosed_30": 2, "diff_netclosed_365": 36, "diff_netclosed_7": 0, "diff_netclosers_30": 2, "diff_netclosers_365": 16, "diff_netclosers_7": 0, "diff_netopened_30": 5, "diff_netopened_365": 26, "diff_netopened_7": 3, "diff_netopeners_30": 5, "diff_netopeners_365": 32, "diff_netopeners_7": 3, "first_date": "2011-05-05", "last_date": "2015-02-15", "opened": 232, "opened_30": 8, "opened_365": 113, "opened_7": 3, "openers": 204, "openers_30": 8, "openers_365": 107, "openers_7": 3, "percentage_bmitickets_30": 12, "percentage_bmitickets_365": 10, "percentage_bmitickets_7": 0, "percentage_changed_30": 100, "percentage_changed_365": 50, "percentage_changed_7": 100, "percentage_changers_30": 200, "percentage_changers_365": 132, "percentage_changers_7": 100, "percentage_closed_30": 200, "percentage_closed_365": 43, "percentage_closed_7": 0, "percentage_closers_30": 200, "percentage_closers_365": 94, "percentage_closers_7": 0, "percentage_opened_30": 166, "percentage_opened_365": 29, "percentage_opened_7": 0, "percentage_openers_30": 166, "percentage_openers_365": 42, "percentage_openers_7": 0, "trackers": 1}